{
  "committees": {
    "Treasurer": "<email-address>",
    "Property": "<email-address>",
    "Fund-raising": "<email-address>",
    "Library": "<email-address>",
    "Administration": "<email-address>",
    "Finance": "<email-address>",
    "Staffing": "<email-address>",
    "Principle": "<email-address>"
  },
  "budgetLineItems": [
    "Admin",
    "Curriculum",
    "Facility Upgrades",
    "Library",
    "Repairs and Maintenance",
    "School Supplies",
    "Sports Equipment and Supplies",
    "Art Supplies"
  ]
}